MANIFEST.in
README.md
requirements.txt
setup.cfg
setup.py
versioneer.py
botcity/plugins/discord/__init__.py
botcity/plugins/discord/_version.py
botcity/plugins/discord/models.py
botcity/plugins/discord/plugin.py
botcity_discord_plugin.egg-info/PKG-INFO
botcity_discord_plugin.egg-info/SOURCES.txt
botcity_discord_plugin.egg-info/dependency_links.txt
botcity_discord_plugin.egg-info/requires.txt
botcity_discord_plugin.egg-info/top_level.txt
tests/test_import.py
tests/test_plugin.py