Metadata-Version: 2.1
Name: botcity-discord-plugin
Version: 0.2.3
Home-page: https://bitbucket.org/botcitydev/bot-discord-plugin-python.git
Requires-Python: >=3.7
